odoo/addons/portal_sale_order_search/README.rst
odoo/addons/portal_sale_order_search/__init__.py
odoo/addons/portal_sale_order_search/__manifest__.py
odoo/addons/portal_sale_order_search/controllers/__init__.py
odoo/addons/portal_sale_order_search/controllers/main.py
odoo/addons/portal_sale_order_search/i18n/es.po
odoo/addons/portal_sale_order_search/i18n/portal_sale_order_search.pot
odoo/addons/portal_sale_order_search/readme/CONTRIBUTORS.md
odoo/addons/portal_sale_order_search/readme/DESCRIPTION.md
odoo/addons/portal_sale_order_search/static/description/icon.png
odoo/addons/portal_sale_order_search/static/description/index.html
odoo_addon_portal_sale_order_search-18.0.1.0.0.2.dist-info/METADATA
odoo_addon_portal_sale_order_search-18.0.1.0.0.2.dist-info/WHEEL
odoo_addon_portal_sale_order_search-18.0.1.0.0.2.dist-info/top_level.txt
odoo_addon_portal_sale_order_search-18.0.1.0.0.2.dist-info/RECORD
